geoformat/__init__.py
geoformat/_version.py
geoformat/conf/__init__.py
geoformat/conf/decorator.py
geoformat/conf/driver_variable.py
geoformat/conf/error_messages.py
geoformat/conf/fields_variable.py
geoformat/conf/format_data.py
geoformat/conf/geoformat_var.py
geoformat/conf/geometry_variable.py
geoformat/conf/path.py
geoformat/conf/proj_var.py
geoformat/conf/timer.py
geoformat/constraints/__init__.py
geoformat/constraints/primary_key.py
geoformat/conversion/__init__.py
geoformat/conversion/bbox_conversion.py
geoformat/conversion/bytes_conversion.py
geoformat/conversion/coordinates_conversion.py
geoformat/conversion/datetime_conversion.py
geoformat/conversion/feature_conversion.py
geoformat/conversion/fields_conversion.py
geoformat/conversion/geolayer_conversion.py
geoformat/conversion/geometry_conversion.py
geoformat/conversion/metadata_conversion.py
geoformat/conversion/precision_tolerance_conversion.py
geoformat/conversion/segment_conversion.py
geoformat/db/__init__.py
geoformat/db/db_request.py
geoformat/draw/__init__.py
geoformat/draw/draw.py
geoformat/driver/__init__.py
geoformat/driver/common_driver.py
geoformat/driver/csv_driver.py
geoformat/driver/esri_shapefile_driver.py
geoformat/driver/geojson_driver.py
geoformat/driver/postgresql_driver.py
geoformat/driver/ogr/__init__.py
geoformat/driver/ogr/ogr_driver.py
geoformat/explore_data/__init__.py
geoformat/explore_data/duplicate.py
geoformat/explore_data/print_data.py
geoformat/explore_data/random_geometry.py
geoformat/geoprocessing/__init__.py
geoformat/geoprocessing/area.py
geoformat/geoprocessing/length.py
geoformat/geoprocessing/line_merge.py
geoformat/geoprocessing/merge_geometries.py
geoformat/geoprocessing/point_on_linestring.py
geoformat/geoprocessing/simplify.py
geoformat/geoprocessing/split.py
geoformat/geoprocessing/union.py
geoformat/geoprocessing/connectors/__init__.py
geoformat/geoprocessing/connectors/operations.py
geoformat/geoprocessing/connectors/predicates.py
geoformat-20250922.dist-info/licenses/LICENSE
geoformat-20250922.dist-info/METADATA
geoformat-20250922.dist-info/WHEEL
geoformat-20250922.dist-info/top_level.txt
geoformat-20250922.dist-info/RECORD
