Metadata-Version: 2.4
Name: geoformat
Version: 20250922
Summary: Geoformat is a 99 % python geospatial blacksmith
Author-email: Guilhain Averlant <g.averlant@mailfence.com>
License: MIT
Project-URL: Homepage, https://framagit.org/Guilhain/Geoformat
Classifier: Development Status :: 3 - Alpha
Classifier: Intended Audience :: Developers
Classifier: Intended Audience :: Science/Research
Classifier: License :: OSI Approved :: MIT License
Classifier: Operating System :: OS Independent
Classifier: Programming Language :: Python
Classifier: Programming Language :: Python :: 3
Classifier: Programming Language :: Python :: 3.8
Classifier: Programming Language :: Python :: 3.9
Classifier: Programming Language :: Python :: 3.10
Classifier: Programming Language :: Python :: 3.11
Classifier: Topic :: Scientific/Engineering :: GIS
License-File: LICENSE
Requires-Dist: numpy
Requires-Dist: matplotlib>=3.7
Requires-Dist: pyproj
Requires-Dist: pyshp
Requires-Dist: psycopg2-binary
Provides-Extra: dev
Requires-Dist: build; extra == "dev"
Requires-Dist: black; extra == "dev"
Provides-Extra: gui
Requires-Dist: PyQt5>=5.15; extra == "gui"
Dynamic: license-file
